{
    "sampleCollection1": {
        "Manuscripts": [
            {},
            {
                "Name": "Sample Manuscript 2",
                "Author": {
                    "Name/Identifier": "Baki"
                },
                "Date": "1684-04-23T18:25:43.511Z"
            }
        ]
    },
    "sampleUser1": {
        "Username": "JohnSmith42", //unique
        "Email": "johnSmith@example.com", //unique
        "First Name": "John",
        "Last Name": "Smith",
        "Title": "Professor of Memeology",
        "Avatar Image": "john.png",
        "Affiliation": "",
        "University": "University of Washington",
        "Department": "Meme Studies",
        "Location": {
            "Country": "USA",
            "State": "Washington",
            "City": "Seattle"
        },
        "Poems": [
            {
                "Name": "samplePoem3",
                "Instance ID": "3", //unique
                "Content ID": "2", //not unique, may be shared with other instances
                "Manuscript": {
                    "Name": "Sample Manuscript 1",
                    "Author": {
                        "Name/Identifier": "Baki" //name of the author?
                    },
                    "Date": "1671-04-23T18:25:43.511Z" //should this be more granular?
                },
                "Collection": {
                    "Name": "Divan",
                    "Location": {
                        "Library": "Suzzallo Library",
                        "Country": "USA",
                        "State": "Washington",
                        "City": "Seattle"
                    }
                },
                "Lines": [
                    {
                        "Comment": {
                            "Author": "SallyJones",
                            "Content": "So fun! I love comments.",
                            "TimeStamp": "2017-05-23T18:25:43.511Z"
                        },
                        "Words": [
                            {
                                "Latin_Text": "Nice",
                                "Arabic_Text": "نيجه‌",
                                "Coded_Text": "Ni6ce0 ",
                                "Comment": {}
                            },
                            {
                                "Latin_Text": "feryada",
                                "Arabic_Text": "فرياده‌",
                                "Coded_Text": "ferya1da0 ",
                                "Comment": {}
                            },
                            {
                                "Latin_Text": "vere",
                                "Arabic_Text": "ويره‌",
                                "Coded_Text": "ve1re0 ",
                                "Comment": {}
                            },
                            {
                                "Latin_Text": "nalelerüm",
                                "Arabic_Text": "ناله‌",
                                "Coded_Text": "na1le0leru0m ",
                                "Comment": {}
                            },
                            {
                                "Latin_Text": "ah",
                                "Arabic_Text": "لرم آه",
                                "Coded_Text": "a2h ",
                                "Comment": {
                                    "Author": "JohnSmith42",
                                    "Content": "difficult to read",
                                    "TimeStamp": "2017-04-23T18:25:43.511Z"
                                }
                            },
                            {
                                "Latin_Text": "sana",
                                "Arabic_Text": "سكا",
                                "Coded_Text": "san6a7 ",
                                "Comment": {}
                            }
                        ]
                    },
                    {
                        "Comment": {},
                        "Words": [
                            {
                                "Latin_Text": "Nice",
                                "Arabic_Text": "نيجه‌",
                                "Coded_Text": "Ni6ce0",
                                "Comment": {}
                            },
                            {
                                "Latin_Text": "ʿarz",
                                "Arabic_Text": "عرض",
                                "Coded_Text": "'2arz4",
                                "Comment": {}
                            },
                            {
                                "Latin_Text": "ideyüm",
                                "Arabic_Text": "ايده‌",
                                "Coded_Text": "i2de0yu0m",
                                "Comment": {}
                            },
                            {
                                "Latin_Text": "halümi",
                                "Arabic_Text": "يم",
                                "Coded_Text": "h3a1lu0mi6",
                                "Comment": {}
                            },
                            {
                                "Latin_Text": "hergah",
                                "Arabic_Text": "حالمى هركاه",
                                "Coded_Text": "herga1h",
                                "Comment": {}
                            },
                            {
                                "Latin_Text": "sana",
                                "Arabic_Text": "سكا",
                                "Coded_Text": "san6a7",
                                "Comment": {}
                            }
                        ]
                    }
                ]
            }
        ]
    },
    "sampleUser2": {
        "Username": "SallyJones", //unique
        "Email": "SallyJones@example.com", //unique
        "First Name": "Sally",
        "Last Name": "Jones",
        "Title": "Associate Professor of Wumbology",
        "Avatar Image": "sally.png",
        "Affiliation": "",
        "University": "University of Washington",
        "Department": "Wumbo",
        "Location": {
            "Country": "USA",
            "State": "Washington",
            "City": "Seattle"
        },
        "Poems": [
            {
                "Name": "SamplePoem1",
                "Instance_ID": "1", //unique
                "Content_ID": "1", //not unique, may be shared with other instances
                "Manuscript": {
                    "Name": "Sample Manuscript 1",
                    "Author": {
                        "Name/Identifier": "Baki" //name of the author?
                    },
                    "Date": "1671-04-23T18:25:43.511Z" //should this be more granular?
                },
                "Collection": {
                    "Name": "Divan",
                    "Location": {
                        "Library": "Suzzallo Library",
                        "Country": "USA",
                        "State": "Washington",
                        "City": "Seattle"
                    }
                },
                "Lines": [
                    {
                        "Comment": {
                            "Author": "SallyJones",
                            "Content": "So fun! I love comments.",
                            "TimeStamp": "2017-05-23T18:25:43.511Z"
                        },
                        "Words": [
                            {
                                "Latin_Text": "Nice",
                                "Arabic_Text": "نيجه‌",
                                "Coded_Text": "Ni6ce0 ",
                                "Comment": {}
                            },
                            {
                                "Latin_Text": "feryada",
                                "Arabic_Text": "فرياده‌",
                                "Coded_Text": "ferya1da0 ",
                                "Comment": {}
                            },
                            {
                                "Latin_Text": "vere",
                                "Arabic_Text": "ويره‌",
                                "Coded_Text": "ve1re0 ",
                                "Comment": {}
                            },
                            {
                                "Latin_Text": "nalelerüm",
                                "Arabic_Text": "ناله‌",
                                "Coded_Text": "na1le0leru0m ",
                                "Comment": {}
                            },
                            {
                                "Latin_Text": "ah",
                                "Arabic_Text": "لرم آه",
                                "Coded_Text": "a2h ",
                                "Comment": {
                                    "Author": "JohnSmith42",
                                    "Content": "difficult to read",
                                    "TimeStamp": "2017-04-23T18:25:43.511Z"
                                }
                            },
                            {
                                "Latin_Text": "sana",
                                "Arabic_Text": "سكا",
                                "Coded_Text": "san6a7 ",
                                "Comment": {}
                            }
                        ]
                    },
                    {
                        "Comment": {},
                        "Words": [
                            {
                                "Latin_Text": "Nice",
                                "Arabic_Text": "نيجه‌",
                                "Coded_Text": "Ni6ce0",
                                "Comment": {}
                            },
                            {
                                "Latin_Text": "ʿarz",
                                "Arabic_Text": "عرض",
                                "Coded_Text": "'2arz4",
                                "Comment": {}
                            },
                            {
                                "Latin_Text": "ideyüm",
                                "Arabic_Text": "ايده‌",
                                "Coded_Text": "i2de0yu0m",
                                "Comment": {}
                            },
                            {
                                "Latin_Text": "halümi",
                                "Arabic_Text": "يم",
                                "Coded_Text": "h3a1lu0mi6",
                                "Comment": {}
                            },
                            {
                                "Latin_Text": "hergah",
                                "Arabic_Text": "حالمى هركاه",
                                "Coded_Text": "herga1h",
                                "Comment": {}
                            },
                            {
                                "Latin_Text": "sana",
                                "Arabic_Text": "سكا",
                                "Coded_Text": "san6a7",
                                "Comment": {}
                            }
                        ]
                    }
                ]
            },
            {
                "Name": "samplePoem2",
                "Instance ID": "2", //unique
                "Content ID": "2", //not unique, may be shared with other instances
                "Manuscript": {
                    "Name": "Sample Manuscript 1",
                    "Author": {
                        "Name/Identifier": "Baki" //name of the author?
                    },
                    "Date": "1671-04-23T18:25:43.511Z" //should this be more granular?
                },
                "Collection": {
                    "Name": "Divan",
                    "Location": {
                        "Library": "Suzzallo Library",
                        "Country": "USA",
                        "State": "Washington",
                        "City": "Seattle"
                    }
                },
                "Lines": [
                    {
                        "Comment": {
                            "Author": "SallyJones",
                            "Content": "So fun! I love comments.",
                            "TimeStamp": "2017-05-23T18:25:43.511Z"
                        },
                        "Words": [
                            {
                                "Latin_Text": "Nice",
                                "Arabic_Text": "نيجه‌",
                                "Coded_Text": "Ni6ce0 ",
                                "Comment": {}
                            },
                            {
                                "Latin_Text": "feryada",
                                "Arabic_Text": "فرياده‌",
                                "Coded_Text": "ferya1da0 ",
                                "Comment": {}
                            },
                            {
                                "Latin_Text": "vere",
                                "Arabic_Text": "ويره‌",
                                "Coded_Text": "ve1re0 ",
                                "Comment": {}
                            },
                            {
                                "Latin_Text": "nalelerüm",
                                "Arabic_Text": "ناله‌",
                                "Coded_Text": "na1le0leru0m ",
                                "Comment": {}
                            },
                            {
                                "Latin_Text": "ah",
                                "Arabic_Text": "لرم آه",
                                "Coded_Text": "a2h ",
                                "Comment": {
                                    "Author": "JohnSmith42",
                                    "Content": "difficult to read",
                                    "TimeStamp": "2017-04-23T18:25:43.511Z"
                                }
                            },
                            {
                                "Latin_Text": "sana",
                                "Arabic_Text": "سكا",
                                "Coded_Text": "san6a7 ",
                                "Comment": {}
                            }
                        ]
                    },
                    {
                        "Comment": {},
                        "Words": [
                            {
                                "Latin_Text": "Nice",
                                "Arabic_Text": "نيجه‌",
                                "Coded_Text": "Ni6ce0",
                                "Comment": {}
                            },
                            {
                                "Latin_Text": "ʿarz",
                                "Arabic_Text": "عرض",
                                "Coded_Text": "'2arz4",
                                "Comment": {}
                            },
                            {
                                "Latin_Text": "ideyüm",
                                "Arabic_Text": "ايده‌",
                                "Coded_Text": "i2de0yu0m",
                                "Comment": {}
                            },
                            {
                                "Latin_Text": "halümi",
                                "Arabic_Text": "يم",
                                "Coded_Text": "h3a1lu0mi6",
                                "Comment": {}
                            },
                            {
                                "Latin_Text": "hergah",
                                "Arabic_Text": "حالمى هركاه",
                                "Coded_Text": "herga1h",
                                "Comment": {}
                            },
                            {
                                "Latin_Text": "sana",
                                "Arabic_Text": "سكا",
                                "Coded_Text": "san6a7",
                                "Comment": {}
                            }
                        ]
                    }
                ]
            }
        ]
    },
    "sampleSession1": {
        "User": "JohnSmith42",
        "Collection": "", //need to figure out an identifier
        "Manuscript": "", //see above
        "InputCodes": "Ni6ce0 ferya1da0 ve1re0 na1le0leru0m a2h san6a7 \\n Ni6ce0 '2arz4 i2de0yu0m h3a1lu0mi6 herga1h san6a7",
        "TimeStamp": "2017-04-25T18:25:43.511Z"
    }
}